{"version":1,"presentation":{"type":"banner","default_placement":{"size":{"width":"100%","height":"auto"},"position":"bottom","shade_color":{"default":{"hex":"#444444","alpha":0.3}}}},"view":{"type":"container","items":[{"position":{"horizontal":"center","vertical":"center"},"size":{"height":"auto","width":"100%"},"margin":{"start":16,"end":16,"bottom":16},"view":{"type":"linear_layout","direction":"horizontal","background_color":{"default":{"hex":"#7F7F7F"}},"border":{"radius":8},"items":[{"size":{"width":"100%","height":"auto"},"weight":1,"view":{"type":"container","items":[{"position":{"horizontal":"center","vertical":"center"},"size":{"width":"100%","height":"auto"},"margin":{"start":16,"end":16},"view":{"type":"label","text":"Help yourself to a snack!","text_appearance":{"font_size":14,"color":{"default":{"hex":"#ffffff"}},"alignment":"start"}}}]}},{"size":{"width":"auto","height":"auto"},"weight":0,"view":{"type":"label_button","identifier":"BUTTON","background_color":{"default":{"hex":"#FF0000","alpha":0}},"button_click":["dismiss"],"label":{"type":"label","text_appearance":{"font_size":14,"alignment":"center","color":{"default":{"hex":"#aeea00"}},"styles":["bold"]},"text":"TASTY"}}}]}}]}}